Metadata-Version: 2.1
Name: pyxterms
Version: 2.0
Summary: A python module to customize terminal and add coloring.
Home-page: https://github.com/lutherantz/pyxterms
Author: akamedagoat
Author-email: akamecanic@gmail.com
License-File: LICENCE.md
